{"season":2026,"stat":{"id":"sv-avg-v-break","title":"Slurve Induced Vert Break","subtitle":"Average slurve induced vertical break.","category":"defense","sort":"desc","unit":"in","formula":"sum of Slurve induced vertical break ÷ Slurve count (min 100 pitches)","leagueAverage":-6.127596214857373,"leagueAverageDisplay":"-6.1 in","leaders":[{"teamId":158,"abbrev":"MIL","teamName":"Milwaukee Brewers","value":-4.006951871657753,"rank":1,"displayValue":"-4.0 in"},{"teamId":121,"abbrev":"NYM","teamName":"New York Mets","value":-4.312318840579711,"rank":2,"displayValue":"-4.3 in"},{"teamId":145,"abbrev":"CWS","teamName":"Chicago White Sox","value":-4.680985915492958,"rank":3,"displayValue":"-4.7 in"},{"teamId":113,"abbrev":"CIN","teamName":"Cincinnati Reds","value":-7.2135746606334825,"rank":4,"displayValue":"-7.2 in"},{"teamId":109,"abbrev":"ARI","teamName":"Arizona Diamondbacks","value":-7.535836909871243,"rank":5,"displayValue":"-7.5 in"},{"teamId":117,"abbrev":"HOU","teamName":"Houston Astros","value":-9.01590909090909,"rank":6,"displayValue":"-9.0 in"}]},"allTeams":[{"teamId":158,"abbrev":"MIL","teamName":"Milwaukee Brewers","value":-4.006951871657753,"rank":1,"displayValue":"-4.0 in"},{"teamId":121,"abbrev":"NYM","teamName":"New York Mets","value":-4.312318840579711,"rank":2,"displayValue":"-4.3 in"},{"teamId":145,"abbrev":"CWS","teamName":"Chicago White Sox","value":-4.680985915492958,"rank":3,"displayValue":"-4.7 in"},{"teamId":113,"abbrev":"CIN","teamName":"Cincinnati Reds","value":-7.2135746606334825,"rank":4,"displayValue":"-7.2 in"},{"teamId":109,"abbrev":"ARI","teamName":"Arizona Diamondbacks","value":-7.535836909871243,"rank":5,"displayValue":"-7.5 in"},{"teamId":117,"abbrev":"HOU","teamName":"Houston Astros","value":-9.01590909090909,"rank":6,"displayValue":"-9.0 in"}],"notableEvents":[],"generatedAt":"2026-07-23T10:19:09.727Z"}
