{"season":2026,"stat":{"id":"si-avg-velocity","title":"Sinker Velo","subtitle":"Average sinker velocity thrown.","category":"defense","sort":"desc","unit":"mph","formula":"sum of Sinker velocities ÷ Sinker count (min 100 pitches)","leagueAverage":94.22763712757519,"leagueAverageDisplay":"94.2 mph","leaders":[{"teamId":136,"abbrev":"SEA","teamName":"Seattle Mariners","value":96.05854341736693,"rank":1,"displayValue":"96.1 mph"},{"teamId":134,"abbrev":"PIT","teamName":"Pittsburgh Pirates","value":95.75374149659865,"rank":2,"displayValue":"95.8 mph"},{"teamId":119,"abbrev":"LAD","teamName":"Los Angeles Dodgers","value":95.72670454545455,"rank":3,"displayValue":"95.7 mph"},{"teamId":158,"abbrev":"MIL","teamName":"Milwaukee Brewers","value":95.61878453038673,"rank":4,"displayValue":"95.6 mph"},{"teamId":145,"abbrev":"CWS","teamName":"Chicago White Sox","value":95.53323699421964,"rank":5,"displayValue":"95.5 mph"},{"teamId":146,"abbrev":"MIA","teamName":"Miami Marlins","value":95.1175,"rank":6,"displayValue":"95.1 mph"},{"teamId":143,"abbrev":"PHI","teamName":"Philadelphia Phillies","value":94.78948374760994,"rank":7,"displayValue":"94.8 mph"},{"teamId":135,"abbrev":"SD","teamName":"San Diego Padres","value":94.75578947368422,"rank":8,"displayValue":"94.8 mph"},{"teamId":108,"abbrev":"LAA","teamName":"Los Angeles Angels","value":94.67,"rank":9,"displayValue":"94.7 mph"},{"teamId":117,"abbrev":"HOU","teamName":"Houston Astros","value":94.61169811320754,"rank":10,"displayValue":"94.6 mph"},{"teamId":142,"abbrev":"MIN","teamName":"Minnesota Twins","value":94.60372670807453,"rank":11,"displayValue":"94.6 mph"},{"teamId":114,"abbrev":"CLE","teamName":"Cleveland Guardians","value":94.54760563380282,"rank":12,"displayValue":"94.5 mph"},{"teamId":111,"abbrev":"BOS","teamName":"Boston Red Sox","value":94.5186974789916,"rank":13,"displayValue":"94.5 mph"},{"teamId":116,"abbrev":"DET","teamName":"Detroit Tigers","value":94.42955801104972,"rank":14,"displayValue":"94.4 mph"},{"teamId":110,"abbrev":"BAL","teamName":"Baltimore Orioles","value":94.39945945945946,"rank":15,"displayValue":"94.4 mph"},{"teamId":121,"abbrev":"NYM","teamName":"New York Mets","value":94.2971181556196,"rank":16,"displayValue":"94.3 mph"},{"teamId":140,"abbrev":"TEX","teamName":"Texas Rangers","value":94.22371541501974,"rank":17,"displayValue":"94.2 mph"},{"teamId":118,"abbrev":"KC","teamName":"Kansas City Royals","value":93.90801603206411,"rank":18,"displayValue":"93.9 mph"},{"teamId":138,"abbrev":"STL","teamName":"St. Louis Cardinals","value":93.88810572687225,"rank":19,"displayValue":"93.9 mph"},{"teamId":147,"abbrev":"NYY","teamName":"New York Yankees","value":93.85613636363635,"rank":20,"displayValue":"93.9 mph"},{"teamId":109,"abbrev":"ARI","teamName":"Arizona Diamondbacks","value":93.8209003215434,"rank":21,"displayValue":"93.8 mph"},{"teamId":137,"abbrev":"SF","teamName":"San Francisco Giants","value":93.71490514905148,"rank":22,"displayValue":"93.7 mph"},{"teamId":139,"abbrev":"TB","teamName":"Tampa Bay Rays","value":93.71315789473682,"rank":23,"displayValue":"93.7 mph"},{"teamId":133,"abbrev":"OAK","teamName":"Athletics","value":93.2434306569343,"rank":24,"displayValue":"93.2 mph"},{"teamId":120,"abbrev":"WSH","teamName":"Washington Nationals","value":93.07074999999999,"rank":25,"displayValue":"93.1 mph"},{"teamId":113,"abbrev":"CIN","teamName":"Cincinnati Reds","value":93.01564102564102,"rank":26,"displayValue":"93.0 mph"},{"teamId":112,"abbrev":"CHC","teamName":"Chicago Cubs","value":92.97656765676568,"rank":27,"displayValue":"93.0 mph"},{"teamId":144,"abbrev":"ATL","teamName":"Atlanta Braves","value":92.82107526881721,"rank":28,"displayValue":"92.8 mph"},{"teamId":141,"abbrev":"TOR","teamName":"Toronto Blue Jays","value":92.74317180616741,"rank":29,"displayValue":"92.7 mph"},{"teamId":115,"abbrev":"COL","teamName":"Colorado Rockies","value":92.40189274447948,"rank":30,"displayValue":"92.4 mph"}]},"allTeams":[{"teamId":136,"abbrev":"SEA","teamName":"Seattle Mariners","value":96.05854341736693,"rank":1,"displayValue":"96.1 mph"},{"teamId":134,"abbrev":"PIT","teamName":"Pittsburgh Pirates","value":95.75374149659865,"rank":2,"displayValue":"95.8 mph"},{"teamId":119,"abbrev":"LAD","teamName":"Los Angeles Dodgers","value":95.72670454545455,"rank":3,"displayValue":"95.7 mph"},{"teamId":158,"abbrev":"MIL","teamName":"Milwaukee Brewers","value":95.61878453038673,"rank":4,"displayValue":"95.6 mph"},{"teamId":145,"abbrev":"CWS","teamName":"Chicago White Sox","value":95.53323699421964,"rank":5,"displayValue":"95.5 mph"},{"teamId":146,"abbrev":"MIA","teamName":"Miami Marlins","value":95.1175,"rank":6,"displayValue":"95.1 mph"},{"teamId":143,"abbrev":"PHI","teamName":"Philadelphia Phillies","value":94.78948374760994,"rank":7,"displayValue":"94.8 mph"},{"teamId":135,"abbrev":"SD","teamName":"San Diego Padres","value":94.75578947368422,"rank":8,"displayValue":"94.8 mph"},{"teamId":108,"abbrev":"LAA","teamName":"Los Angeles Angels","value":94.67,"rank":9,"displayValue":"94.7 mph"},{"teamId":117,"abbrev":"HOU","teamName":"Houston Astros","value":94.61169811320754,"rank":10,"displayValue":"94.6 mph"},{"teamId":142,"abbrev":"MIN","teamName":"Minnesota Twins","value":94.60372670807453,"rank":11,"displayValue":"94.6 mph"},{"teamId":114,"abbrev":"CLE","teamName":"Cleveland Guardians","value":94.54760563380282,"rank":12,"displayValue":"94.5 mph"},{"teamId":111,"abbrev":"BOS","teamName":"Boston Red Sox","value":94.5186974789916,"rank":13,"displayValue":"94.5 mph"},{"teamId":116,"abbrev":"DET","teamName":"Detroit Tigers","value":94.42955801104972,"rank":14,"displayValue":"94.4 mph"},{"teamId":110,"abbrev":"BAL","teamName":"Baltimore Orioles","value":94.39945945945946,"rank":15,"displayValue":"94.4 mph"},{"teamId":121,"abbrev":"NYM","teamName":"New York Mets","value":94.2971181556196,"rank":16,"displayValue":"94.3 mph"},{"teamId":140,"abbrev":"TEX","teamName":"Texas Rangers","value":94.22371541501974,"rank":17,"displayValue":"94.2 mph"},{"teamId":118,"abbrev":"KC","teamName":"Kansas City Royals","value":93.90801603206411,"rank":18,"displayValue":"93.9 mph"},{"teamId":138,"abbrev":"STL","teamName":"St. Louis Cardinals","value":93.88810572687225,"rank":19,"displayValue":"93.9 mph"},{"teamId":147,"abbrev":"NYY","teamName":"New York Yankees","value":93.85613636363635,"rank":20,"displayValue":"93.9 mph"},{"teamId":109,"abbrev":"ARI","teamName":"Arizona Diamondbacks","value":93.8209003215434,"rank":21,"displayValue":"93.8 mph"},{"teamId":137,"abbrev":"SF","teamName":"San Francisco Giants","value":93.71490514905148,"rank":22,"displayValue":"93.7 mph"},{"teamId":139,"abbrev":"TB","teamName":"Tampa Bay Rays","value":93.71315789473682,"rank":23,"displayValue":"93.7 mph"},{"teamId":133,"abbrev":"OAK","teamName":"Athletics","value":93.2434306569343,"rank":24,"displayValue":"93.2 mph"},{"teamId":120,"abbrev":"WSH","teamName":"Washington Nationals","value":93.07074999999999,"rank":25,"displayValue":"93.1 mph"},{"teamId":113,"abbrev":"CIN","teamName":"Cincinnati Reds","value":93.01564102564102,"rank":26,"displayValue":"93.0 mph"},{"teamId":112,"abbrev":"CHC","teamName":"Chicago Cubs","value":92.97656765676568,"rank":27,"displayValue":"93.0 mph"},{"teamId":144,"abbrev":"ATL","teamName":"Atlanta Braves","value":92.82107526881721,"rank":28,"displayValue":"92.8 mph"},{"teamId":141,"abbrev":"TOR","teamName":"Toronto Blue Jays","value":92.74317180616741,"rank":29,"displayValue":"92.7 mph"},{"teamId":115,"abbrev":"COL","teamName":"Colorado Rockies","value":92.40189274447948,"rank":30,"displayValue":"92.4 mph"}],"notableEvents":[],"generatedAt":"2026-07-13T10:58:17.914Z"}
